accdbtools.py
accdbtools-0.0.3.dist-info/METADATA
accdbtools-0.0.3.dist-info/WHEEL
accdbtools-0.0.3.dist-info/RECORD
